{"nodes": [{"usage": 69, "group": "Grass", "gxe95": 47, "gxeMax": 57, "img": "https://play.pokemonshowdown.com/sprites/bw/bulbasaur.png", "id": "Bulbasaur"}, {"usage": 11, "group": "Grass", "gxe95": 45, "gxeMax": 55, "img": "https://play.pokemonshowdown.com/sprites/bw/ivysaur.png", "id": "Ivysaur"}, {"usage": 722, "group": "Grass", "gxe95": 55, "gxeMax": 90, "img": "https://play.pokemonshowdown.com/sprites/bw/venusaur.png", "id": "Venusaur"}, {"usage": 25, "group": "Fire", "gxe95": 46, "gxeMax": 57, "img": "https://play.pokemonshowdown.com/sprites/bw/charmander.png", "id": "Charmander"}, {"usage": 17, "group": "Fire", "gxe95": 47, "gxeMax": 58, "img": "https://play.pokemonshowdown.com/sprites/bw/charmeleon.png", "id": "Charmeleon"}, {"usage": 1264, "group": "Fire", "gxe95": 55, "gxeMax": 77, "img": "https://play.pokemonshowdown.com/sprites/bw/charizard.png", "id": "Charizard"}, {"usage": 57, "group": "Water", "gxe95": 51, "gxeMax": 57, "img": "https://play.pokemonshowdown.com/sprites/bw/squirtle.png", "id": "Squirtle"}, {"usage": 13, "group": "Water", "gxe95": 55, "gxeMax": 57, "img": "https://play.pokemonshowdown.com/sprites/bw/wartortle.png", "id": "Wartortle"}, {"usage": 616, "group": "Water", "gxe95": 54, "gxeMax": 77, "img": "https://play.pokemonshowdown.com/sprites/bw/blastoise.png", "id": "Blastoise"}, {"usage": 6, "group": "Bug", "gxe95": 47, "gxeMax": 51, "img": "https://play.pokemonshowdown.com/sprites/bw/caterpie.png", "id": "Caterpie"}, {"usage": 4, "group": "Bug", "gxe95": 51, "gxeMax": 51, "img": "https://play.pokemonshowdown.com/sprites/bw/metapod.png", "id": "Metapod"}, {"usage": 75, "group": "Bug", "gxe95": 49, "gxeMax": 63, "img": "https://play.pokemonshowdown.com/sprites/bw/butterfree.png", "id": "Butterfree"}, {"usage": 5, "group": "Bug", "gxe95": 51, "gxeMax": 51, "img": "https://play.pokemonshowdown.com/sprites/bw/weedle.png", "id": "Weedle"}, {"usage": 0, "group": "Bug", "gxe95": 0, "gxeMax": 0, "img": "https://play.pokemonshowdown.com/sprites/bw/kakuna.png", "id": "Kakuna"}, {"usage": 60, "group": "Bug", "gxe95": 55, "gxeMax": 78, "img": "https://play.pokemonshowdown.com/sprites/bw/beedrill.png", "id": "Beedrill"}, {"usage": 4, "group": "Normal", "gxe95": 45, "gxeMax": 45, "img": "https://play.pokemonshowdown.com/sprites/bw/pidgey.png", "id": "Pidgey"}, {"usage": 19, "group": "Normal", "gxe95": 46, "gxeMax": 58, "img": "https://play.pokemonshowdown.com/sprites/bw/pidgeotto.png", "id": "Pidgeotto"}, {"usage": 239, "group": "Normal", "gxe95": 53, "gxeMax": 63, "img": "https://play.pokemonshowdown.com/sprites/bw/pidgeot.png", "id": "Pidgeot"}, {"usage": 10, "group": "Normal", "gxe95": 45, "gxeMax": 46, "img": "https://play.pokemonshowdown.com/sprites/bw/rattata.png", "id": "Rattata"}, {"usage": 33, "group": "Normal", "gxe95": 54, "gxeMax": 71, "img": "https://play.pokemonshowdown.com/sprites/bw/raticate.png", "id": "Raticate"}, {"usage": 0, "group": "Normal", "gxe95": 0, "gxeMax": 0, "img": "https://play.pokemonshowdown.com/sprites/bw/spearow.png", "id": "Spearow"}, {"usage": 29, "group": "Normal", "gxe95": 55, "gxeMax": 70, "img": "https://play.pokemonshowdown.com/sprites/bw/fearow.png", "id": "Fearow"}, {"usage": 5, "group": "Poison", "gxe95": 55, "gxeMax": 55, "img": "https://play.pokemonshowdown.com/sprites/bw/ekans.png", "id": "Ekans"}, {"usage": 77, "group": "Poison", "gxe95": 53, "gxeMax": 66, "img": "https://play.pokemonshowdown.com/sprites/bw/arbok.png", "id": "Arbok"}, {"usage": 261, "group": "Electric", "gxe95": 53, "gxeMax": 72, "img": "https://play.pokemonshowdown.com/sprites/bw/pikachu.png", "id": "Pikachu"}, {"usage": 336, "group": "Electric", "gxe95": 55, "gxeMax": 80, "img": "https://play.pokemonshowdown.com/sprites/bw/raichu.png", "id": "Raichu"}, {"usage": 0, "group": "Ground", "gxe95": 0, "gxeMax": 0, "img": "https://play.pokemonshowdown.com/sprites/bw/sandshrew.png", "id": "Sandshrew"}, {"usage": 70, "group": "Ground", "gxe95": 58, "gxeMax": 82, "img": "https://play.pokemonshowdown.com/sprites/bw/sandslash.png", "id": "Sandslash"}, {"usage": 0, "group": "Poison", "gxe95": 0, "gxeMax": 0, "img": "https://play.pokemonshowdown.com/sprites/bw/nidoranf.png", "id": "NidoranF"}, {"usage": 3, "group": "Poison", "gxe95": 45, "gxeMax": 45, "img": "https://play.pokemonshowdown.com/sprites/bw/nidorina.png", "id": "Nidorina"}, {"usage": 57, "group": "Poison", "gxe95": 55, "gxeMax": 72, "img": "https://play.pokemonshowdown.com/sprites/bw/nidoqueen.png", "id": "Nidoqueen"}, {"usage": 0, "group": "Poison", "gxe95": 0, "gxeMax": 0, "img": "https://play.pokemonshowdown.com/sprites/bw/nidoranm.png", "id": "NidoranM"}, {"usage": 4, "group": "Poison", "gxe95": 45, "gxeMax": 45, "img": "https://play.pokemonshowdown.com/sprites/bw/nidorino.png", "id": "Nidorino"}, {"usage": 285, "group": "Poison", "gxe95": 55, "gxeMax": 72, "img": "https://play.pokemonshowdown.com/sprites/bw/nidoking.png", "id": "Nidoking"}, {"usage": 1, "group": "Normal", "gxe95": 29, "gxeMax": 29, "img": "https://play.pokemonshowdown.com/sprites/bw/clefairy.png", "id": "Clefairy"}, {"usage": 81, "group": "Normal", "gxe95": 55, "gxeMax": 83, "img": "https://play.pokemonshowdown.com/sprites/bw/clefable.png", "id": "Clefable"}, {"usage": 10, "group": "Fire", "gxe95": 47, "gxeMax": 50, "img": "https://play.pokemonshowdown.com/sprites/bw/vulpix.png", "id": "Vulpix"}, {"usage": 155, "group": "Fire", "gxe95": 55, "gxeMax": 82, "img": "https://play.pokemonshowdown.com/sprites/bw/ninetales.png", "id": "Ninetales"}, {"usage": 11, "group": "Normal", "gxe95": 45, "gxeMax": 46, "img": "https://play.pokemonshowdown.com/sprites/bw/jigglypuff.png", "id": "Jigglypuff"}, {"usage": 42, "group": "Normal", "gxe95": 56, "gxeMax": 75, "img": "https://play.pokemonshowdown.com/sprites/bw/wigglytuff.png", "id": "Wigglytuff"}, {"usage": 7, "group": "Poison", "gxe95": 46, "gxeMax": 55, "img": "https://play.pokemonshowdown.com/sprites/bw/zubat.png", "id": "Zubat"}, {"usage": 31, "group": "Poison", "gxe95": 54, "gxeMax": 57, "img": "https://play.pokemonshowdown.com/sprites/bw/golbat.png", "id": "Golbat"}, {"usage": 0, "group": "Grass", "gxe95": 0, "gxeMax": 0, "img": "https://play.pokemonshowdown.com/sprites/bw/oddish.png", "id": "Oddish"}, {"usage": 6, "group": "Grass", "gxe95": 53, "gxeMax": 55, "img": "https://play.pokemonshowdown.com/sprites/bw/gloom.png", "id": "Gloom"}, {"usage": 57, "group": "Grass", "gxe95": 51, "gxeMax": 67, "img": "https://play.pokemonshowdown.com/sprites/bw/vileplume.png", "id": "Vileplume"}, {"usage": 0, "group": "Bug", "gxe95": 0, "gxeMax": 0, "img": "https://play.pokemonshowdown.com/sprites/bw/paras.png", "id": "Paras"}, {"usage": 52, "group": "Bug", "gxe95": 55, "gxeMax": 75, "img": "https://play.pokemonshowdown.com/sprites/bw/parasect.png", "id": "Parasect"}, {"usage": 0, "group": "Bug", "gxe95": 0, "gxeMax": 0, "img": "https://play.pokemonshowdown.com/sprites/bw/venonat.png", "id": "Venonat"}, {"usage": 41, "group": "Bug", "gxe95": 55, "gxeMax": 71, "img": "https://play.pokemonshowdown.com/sprites/bw/venomoth.png", "id": "Venomoth"}, {"usage": 3, "group": "Ground", "gxe95": 45, "gxeMax": 45, "img": "https://play.pokemonshowdown.com/sprites/bw/diglett.png", "id": "Diglett"}, {"usage": 96, "group": "Ground", "gxe95": 61, "gxeMax": 72, "img": "https://play.pokemonshowdown.com/sprites/bw/dugtrio.png", "id": "Dugtrio"}, {"usage": 14, "group": "Normal", "gxe95": 55, "gxeMax": 60, "img": "https://play.pokemonshowdown.com/sprites/bw/meowth.png", "id": "Meowth"}, {"usage": 234, "group": "Normal", "gxe95": 62, "gxeMax": 91, "img": "https://play.pokemonshowdown.com/sprites/bw/persian.png", "id": "Persian"}, {"usage": 10, "group": "Water", "gxe95": 45, "gxeMax": 56, "img": "https://play.pokemonshowdown.com/sprites/bw/psyduck.png", "id": "Psyduck"}, {"usage": 68, "group": "Water", "gxe95": 55, "gxeMax": 88, "img": "https://play.pokemonshowdown.com/sprites/bw/golduck.png", "id": "Golduck"}, {"usage": 0, "group": "Fighting", "gxe95": 0, "gxeMax": 0, "img": "https://play.pokemonshowdown.com/sprites/bw/mankey.png", "id": "Mankey"}, {"usage": 61, "group": "Fighting", "gxe95": 55, "gxeMax": 65, "img": "https://play.pokemonshowdown.com/sprites/bw/primeape.png", "id": "Primeape"}, {"usage": 6, "group": "Fire", "gxe95": 45, "gxeMax": 60, "img": "https://play.pokemonshowdown.com/sprites/bw/growlithe.png", "id": "Growlithe"}, {"usage": 423, "group": "Fire", "gxe95": 55, "gxeMax": 72, "img": "https://play.pokemonshowdown.com/sprites/bw/arcanine.png", "id": "Arcanine"}, {"usage": 3, "group": "Water", "gxe95": 56, "gxeMax": 56, "img": "https://play.pokemonshowdown.com/sprites/bw/poliwag.png", "id": "Poliwag"}, {"usage": 5, "group": "Water", "gxe95": 55, "gxeMax": 55, "img": "https://play.pokemonshowdown.com/sprites/bw/poliwhirl.png", "id": "Poliwhirl"}, {"usage": 112, "group": "Water", "gxe95": 55, "gxeMax": 74, "img": "https://play.pokemonshowdown.com/sprites/bw/poliwrath.png", "id": "Poliwrath"}, {"usage": 10, "group": "Psychic", "gxe95": 47, "gxeMax": 47, "img": "https://play.pokemonshowdown.com/sprites/bw/abra.png", "id": "Abra"}, {"usage": 27, "group": "Psychic", "gxe95": 55, "gxeMax": 69, "img": "https://play.pokemonshowdown.com/sprites/bw/kadabra.png", "id": "Kadabra"}, {"usage": 2223, "group": "Psychic", "gxe95": 60, "gxeMax": 91, "img": "https://play.pokemonshowdown.com/sprites/bw/alakazam.png", "id": "Alakazam"}, {"usage": 0, "group": "Fighting", "gxe95": 0, "gxeMax": 0, "img": "https://play.pokemonshowdown.com/sprites/bw/machop.png", "id": "Machop"}, {"usage": 8, "group": "Fighting", "gxe95": 48, "gxeMax": 55, "img": "https://play.pokemonshowdown.com/sprites/bw/machoke.png", "id": "Machoke"}, {"usage": 264, "group": "Fighting", "gxe95": 55, "gxeMax": 70, "img": "https://play.pokemonshowdown.com/sprites/bw/machamp.png", "id": "Machamp"}, {"usage": 0, "group": "Grass", "gxe95": 0, "gxeMax": 0, "img": "https://play.pokemonshowdown.com/sprites/bw/bellsprout.png", "id": "Bellsprout"}, {"usage": 4, "group": "Grass", "gxe95": 50, "gxeMax": 50, "img": "https://play.pokemonshowdown.com/sprites/bw/weepinbell.png", "id": "Weepinbell"}, {"usage": 163, "group": "Grass", "gxe95": 59, "gxeMax": 89, "img": "https://play.pokemonshowdown.com/sprites/bw/victreebel.png", "id": "Victreebel"}, {"usage": 76, "group": "Water", "gxe95": 56, "gxeMax": 71, "img": "https://play.pokemonshowdown.com/sprites/bw/tentacruel.png", "id": "Tentacruel"}, {"usage": 8, "group": "Rock", "gxe95": 45, "gxeMax": 55, "img": "https://play.pokemonshowdown.com/sprites/bw/geodude.png", "id": "Geodude"}, {"usage": 19, "group": "Rock", "gxe95": 55, "gxeMax": 55, "img": "https://play.pokemonshowdown.com/sprites/bw/graveler.png", "id": "Graveler"}, {"usage": 997, "group": "Rock", "gxe95": 62, "gxeMax": 91, "img": "https://play.pokemonshowdown.com/sprites/bw/golem.png", "id": "Golem"}, {"usage": 4, "group": "Fire", "gxe95": 43, "gxeMax": 43, "img": "https://play.pokemonshowdown.com/sprites/bw/ponyta.png", "id": "Ponyta"}, {"usage": 65, "group": "Fire", "gxe95": 55, "gxeMax": 69, "img": "https://play.pokemonshowdown.com/sprites/bw/rapidash.png", "id": "Rapidash"}, {"usage": 3, "group": "Water", "gxe95": 56, "gxeMax": 56, "img": "https://play.pokemonshowdown.com/sprites/bw/slowpoke.png", "id": "Slowpoke"}, {"usage": 708, "group": "Water", "gxe95": 63, "gxeMax": 91, "img": "https://play.pokemonshowdown.com/sprites/bw/slowbro.png", "id": "Slowbro"}, {"usage": 4, "group": "Electric", "gxe95": 48, "gxeMax": 48, "img": "https://play.pokemonshowdown.com/sprites/bw/magnemite.png", "id": "Magnemite"}, {"usage": 68, "group": "Electric", "gxe95": 55, "gxeMax": 59, "img": "https://play.pokemonshowdown.com/sprites/bw/magneton.png", "id": "Magneton"}, {"usage": 26, "group": "Normal", "gxe95": 50, "gxeMax": 70, "img": "https://play.pokemonshowdown.com/sprites/bw/farfetchd.png", "id": "Farfetch'd"}, {"usage": 166, "group": "Normal", "gxe95": 55, "gxeMax": 88, "img": "https://play.pokemonshowdown.com/sprites/bw/dodrio.png", "id": "Dodrio"}, {"usage": 3, "group": "Water", "gxe95": 36, "gxeMax": 36, "img": "https://play.pokemonshowdown.com/sprites/bw/seel.png", "id": "Seel"}, {"usage": 51, "group": "Water", "gxe95": 50, "gxeMax": 59, "img": "https://play.pokemonshowdown.com/sprites/bw/dewgong.png", "id": "Dewgong"}, {"usage": 91, "group": "Poison", "gxe95": 52, "gxeMax": 59, "img": "https://play.pokemonshowdown.com/sprites/bw/muk.png", "id": "Muk"}, {"usage": 0, "group": "Water", "gxe95": 0, "gxeMax": 0, "img": "https://play.pokemonshowdown.com/sprites/bw/shellder.png", "id": "Shellder"}, {"usage": 597, "group": "Water", "gxe95": 61, "gxeMax": 91, "img": "https://play.pokemonshowdown.com/sprites/bw/cloyster.png", "id": "Cloyster"}, {"usage": 9, "group": "Ghost", "gxe95": 55, "gxeMax": 65, "img": "https://play.pokemonshowdown.com/sprites/bw/gastly.png", "id": "Gastly"}, {"usage": 32, "group": "Ghost", "gxe95": 54, "gxeMax": 65, "img": "https://play.pokemonshowdown.com/sprites/bw/haunter.png", "id": "Haunter"}, {"usage": 1814, "group": "Ghost", "gxe95": 57, "gxeMax": 92, "img": "https://play.pokemonshowdown.com/sprites/bw/gengar.png", "id": "Gengar"}, {"usage": 68, "group": "Rock", "gxe95": 54, "gxeMax": 62, "img": "https://play.pokemonshowdown.com/sprites/bw/onix.png", "id": "Onix"}, {"usage": 3, "group": "Psychic", "gxe95": 57, "gxeMax": 57, "img": "https://play.pokemonshowdown.com/sprites/bw/drowzee.png", "id": "Drowzee"}, {"usage": 93, "group": "Psychic", "gxe95": 60, "gxeMax": 89, "img": "https://play.pokemonshowdown.com/sprites/bw/hypno.png", "id": "Hypno"}, {"usage": 7, "group": "Water", "gxe95": 45, "gxeMax": 46, "img": "https://play.pokemonshowdown.com/sprites/bw/krabby.png", "id": "Krabby"}, {"usage": 77, "group": "Water", "gxe95": 55, "gxeMax": 88, "img": "https://play.pokemonshowdown.com/sprites/bw/kingler.png", "id": "Kingler"}, {"usage": 8, "group": "Electric", "gxe95": 45, "gxeMax": 48, "img": "https://play.pokemonshowdown.com/sprites/bw/voltorb.png", "id": "Voltorb"}, {"usage": 152, "group": "Electric", "gxe95": 57, "gxeMax": 76, "img": "https://play.pokemonshowdown.com/sprites/bw/electrode.png", "id": "Electrode"}, {"usage": 7, "group": "Grass", "gxe95": 47, "gxeMax": 59, "img": "https://play.pokemonshowdown.com/sprites/bw/exeggcute.png", "id": "Exeggcute"}, {"usage": 1591, "group": "Grass", "gxe95": 67, "gxeMax": 92, "img": "https://play.pokemonshowdown.com/sprites/bw/exeggutor.png", "id": "Exeggutor"}, {"usage": 5, "group": "Ground", "gxe95": 50, "gxeMax": 50, "img": "https://play.pokemonshowdown.com/sprites/bw/cubone.png", "id": "Cubone"}, {"usage": 80, "group": "Ground", "gxe95": 53, "gxeMax": 60, "img": "https://play.pokemonshowdown.com/sprites/bw/marowak.png", "id": "Marowak"}, {"usage": 144, "group": "Fighting", "gxe95": 55, "gxeMax": 69, "img": "https://play.pokemonshowdown.com/sprites/bw/hitmonlee.png", "id": "Hitmonlee"}, {"usage": 78, "group": "Fighting", "gxe95": 54, "gxeMax": 63, "img": "https://play.pokemonshowdown.com/sprites/bw/hitmonchan.png", "id": "Hitmonchan"}, {"usage": 36, "group": "Normal", "gxe95": 55, "gxeMax": 66, "img": "https://play.pokemonshowdown.com/sprites/bw/lickitung.png", "id": "Lickitung"}, {"usage": 3, "group": "Poison", "gxe95": 55, "gxeMax": 55, "img": "https://play.pokemonshowdown.com/sprites/bw/koffing.png", "id": "Koffing"}, {"usage": 52, "group": "Poison", "gxe95": 55, "gxeMax": 63, "img": "https://play.pokemonshowdown.com/sprites/bw/weezing.png", "id": "Weezing"}, {"usage": 12, "group": "Ground", "gxe95": 46, "gxeMax": 55, "img": "https://play.pokemonshowdown.com/sprites/bw/rhyhorn.png", "id": "Rhyhorn"}, {"usage": 1037, "group": "Ground", "gxe95": 61, "gxeMax": 94, "img": "https://play.pokemonshowdown.com/sprites/bw/rhydon.png", "id": "Rhydon"}, {"usage": 1555, "group": "Normal", "gxe95": 67, "gxeMax": 94, "img": "https://play.pokemonshowdown.com/sprites/bw/chansey.png", "id": "Chansey"}, {"usage": 30, "group": "Grass", "gxe95": 55, "gxeMax": 66, "img": "https://play.pokemonshowdown.com/sprites/bw/tangela.png", "id": "Tangela"}, {"usage": 106, "group": "Normal", "gxe95": 59, "gxeMax": 91, "img": "https://play.pokemonshowdown.com/sprites/bw/kangaskhan.png", "id": "Kangaskhan"}, {"usage": 8, "group": "Water", "gxe95": 47, "gxeMax": 56, "img": "https://play.pokemonshowdown.com/sprites/bw/horsea.png", "id": "Horsea"}, {"usage": 24, "group": "Water", "gxe95": 50, "gxeMax": 59, "img": "https://play.pokemonshowdown.com/sprites/bw/seadra.png", "id": "Seadra"}, {"usage": 4, "group": "Water", "gxe95": 56, "gxeMax": 56, "img": "https://play.pokemonshowdown.com/sprites/bw/goldeen.png", "id": "Goldeen"}, {"usage": 8, "group": "Water", "gxe95": 46, "gxeMax": 46, "img": "https://play.pokemonshowdown.com/sprites/bw/seaking.png", "id": "Seaking"}, {"usage": 13, "group": "Water", "gxe95": 56, "gxeMax": 59, "img": "https://play.pokemonshowdown.com/sprites/bw/staryu.png", "id": "Staryu"}, {"usage": 911, "group": "Water", "gxe95": 68, "gxeMax": 94, "img": "https://play.pokemonshowdown.com/sprites/bw/starmie.png", "id": "Starmie"}, {"usage": 44, "group": "Psychic", "gxe95": 55, "gxeMax": 70, "img": "https://play.pokemonshowdown.com/sprites/bw/mrmime.png", "id": "Mr. Mime"}, {"usage": 124, "group": "Bug", "gxe95": 54, "gxeMax": 66, "img": "https://play.pokemonshowdown.com/sprites/bw/scyther.png", "id": "Scyther"}, {"usage": 443, "group": "Ice", "gxe95": 75, "gxeMax": 94, "img": "https://play.pokemonshowdown.com/sprites/bw/jynx.png", "id": "Jynx"}, {"usage": 99, "group": "Electric", "gxe95": 54, "gxeMax": 71, "img": "https://play.pokemonshowdown.com/sprites/bw/electabuzz.png", "id": "Electabuzz"}, {"usage": 59, "group": "Fire", "gxe95": 54, "gxeMax": 65, "img": "https://play.pokemonshowdown.com/sprites/bw/magmar.png", "id": "Magmar"}, {"usage": 44, "group": "Bug", "gxe95": 58, "gxeMax": 83, "img": "https://play.pokemonshowdown.com/sprites/bw/pinsir.png", "id": "Pinsir"}, {"usage": 1332, "group": "Normal", "gxe95": 70, "gxeMax": 94, "img": "https://play.pokemonshowdown.com/sprites/bw/tauros.png", "id": "Tauros"}, {"usage": 17, "group": "Water", "gxe95": 47, "gxeMax": 80, "img": "https://play.pokemonshowdown.com/sprites/bw/magikarp.png", "id": "Magikarp"}, {"usage": 385, "group": "Water", "gxe95": 55, "gxeMax": 75, "img": "https://play.pokemonshowdown.com/sprites/bw/gyarados.png", "id": "Gyarados"}, {"usage": 1154, "group": "Water", "gxe95": 58, "gxeMax": 91, "img": "https://play.pokemonshowdown.com/sprites/bw/lapras.png", "id": "Lapras"}, {"usage": 136, "group": "Normal", "gxe95": 54, "gxeMax": 66, "img": "https://play.pokemonshowdown.com/sprites/bw/ditto.png", "id": "Ditto"}, {"usage": 19, "group": "Normal", "gxe95": 48, "gxeMax": 68, "img": "https://play.pokemonshowdown.com/sprites/bw/eevee.png", "id": "Eevee"}, {"usage": 150, "group": "Water", "gxe95": 55, "gxeMax": 75, "img": "https://play.pokemonshowdown.com/sprites/bw/vaporeon.png", "id": "Vaporeon"}, {"usage": 1089, "group": "Electric", "gxe95": 57, "gxeMax": 91, "img": "https://play.pokemonshowdown.com/sprites/bw/jolteon.png", "id": "Jolteon"}, {"usage": 112, "group": "Fire", "gxe95": 53, "gxeMax": 77, "img": "https://play.pokemonshowdown.com/sprites/bw/flareon.png", "id": "Flareon"}, {"usage": 43, "group": "Normal", "gxe95": 54, "gxeMax": 64, "img": "https://play.pokemonshowdown.com/sprites/bw/porygon.png", "id": "Porygon"}, {"usage": 3, "group": "Rock", "gxe95": 50, "gxeMax": 50, "img": "https://play.pokemonshowdown.com/sprites/bw/omanyte.png", "id": "Omanyte"}, {"usage": 51, "group": "Rock", "gxe95": 55, "gxeMax": 69, "img": "https://play.pokemonshowdown.com/sprites/bw/omastar.png", "id": "Omastar"}, {"usage": 4, "group": "Rock", "gxe95": 50, "gxeMax": 50, "img": "https://play.pokemonshowdown.com/sprites/bw/kabuto.png", "id": "Kabuto"}, {"usage": 78, "group": "Rock", "gxe95": 55, "gxeMax": 72, "img": "https://play.pokemonshowdown.com/sprites/bw/kabutops.png", "id": "Kabutops"}, {"usage": 195, "group": "Rock", "gxe95": 55, "gxeMax": 67, "img": "https://play.pokemonshowdown.com/sprites/bw/aerodactyl.png", "id": "Aerodactyl"}, {"usage": 1805, "group": "Normal", "gxe95": 63, "gxeMax": 94, "img": "https://play.pokemonshowdown.com/sprites/bw/snorlax.png", "id": "Snorlax"}, {"usage": 308, "group": "Ice", "gxe95": 55, "gxeMax": 84, "img": "https://play.pokemonshowdown.com/sprites/bw/articuno.png", "id": "Articuno"}, {"usage": 1161, "group": "Electric", "gxe95": 62, "gxeMax": 92, "img": "https://play.pokemonshowdown.com/sprites/bw/zapdos.png", "id": "Zapdos"}, {"usage": 236, "group": "Fire", "gxe95": 55, "gxeMax": 73, "img": "https://play.pokemonshowdown.com/sprites/bw/moltres.png", "id": "Moltres"}, {"usage": 6, "group": "Dragon", "gxe95": 65, "gxeMax": 66, "img": "https://play.pokemonshowdown.com/sprites/bw/dratini.png", "id": "Dratini"}, {"usage": 42, "group": "Dragon", "gxe95": 60, "gxeMax": 67, "img": "https://play.pokemonshowdown.com/sprites/bw/dragonair.png", "id": "Dragonair"}, {"usage": 1100, "group": "Dragon", "gxe95": 55, "gxeMax": 87, "img": "https://play.pokemonshowdown.com/sprites/bw/dragonite.png", "id": "Dragonite"}], "links": [{"target": "Pikachu", "value": 66, "source": "Bulbasaur"}, {"target": "Charizard", "value": 17, "source": "Ivysaur"}, {"target": "Blastoise", "value": 535, "source": "Venusaur"}, {"target": "Pikachu", "value": 7, "source": "Charmander"}, {"target": "Ditto", "value": 3, "source": "Charmeleon"}, {"target": "Blastoise", "value": 615, "source": "Charizard"}, {"target": "Pikachu", "value": 68, "source": "Squirtle"}, {"target": "Charizard", "value": 4, "source": "Wartortle"}, {"target": "Charizard", "value": 614, "source": "Blastoise"}, {"target": "Weedle", "value": 3, "source": "Caterpie"}, {"target": "Magikarp", "value": 4, "source": "Metapod"}, {"target": "Charizard", "value": 42, "source": "Butterfree"}, {"target": "Electabuzz", "value": 4, "source": "Weedle"}, {"target": "Onix", "value": 20, "source": "Beedrill"}, {"target": "Charmander", "value": 2, "source": "Pidgey"}, {"target": "Pikachu", "value": 11, "source": "Pidgeotto"}, {"target": "Charizard", "value": 172, "source": "Pidgeot"}, {"target": "Magikarp", "value": 4, "source": "Rattata"}, {"target": "Hypno", "value": 17, "source": "Raticate"}, {"target": "Sandslash", "value": 15, "source": "Fearow"}, {"target": "Krabby", "value": 1, "source": "Ekans"}, {"target": "Lickitung", "value": 25, "source": "Arbok"}, {"target": "Charizard", "value": 342, "source": "Pikachu"}, {"target": "Nidoking", "value": 164, "source": "Raichu"}, {"target": "Ninetales", "value": 22, "source": "Sandslash"}, {"target": "Venonat", "value": 1, "source": "Nidorina"}, {"target": "Clefable", "value": 132, "source": "Nidoqueen"}, {"target": "Beedrill", "value": 2, "source": "Nidorino"}, {"target": "Charizard", "value": 198, "source": "Nidoking"}, {"target": "Wigglytuff", "value": 3, "source": "Clefairy"}, {"target": "Hypno", "value": 149, "source": "Clefable"}, {"target": "Charmeleon", "value": 2, "source": "Vulpix"}, {"target": "Dragonite", "value": 86, "source": "Ninetales"}, {"target": "Bulbasaur", "value": 8, "source": "Jigglypuff"}, {"target": "Raichu", "value": 44, "source": "Wigglytuff"}, {"target": "Rattata", "value": 3, "source": "Zubat"}, {"target": "Hypno", "value": 11, "source": "Golbat"}, {"target": "Golduck", "value": 5, "source": "Gloom"}, {"target": "Charizard", "value": 42, "source": "Vileplume"}, {"target": "Dewgong", "value": 15, "source": "Parasect"}, {"target": "Omastar", "value": 30, "source": "Venomoth"}, {"target": "Horsea", "value": 1, "source": "Diglett"}, {"target": "Gyarados", "value": 47, "source": "Dugtrio"}, {"target": "Golbat", "value": 7, "source": "Meowth"}, {"target": "Dodrio", "value": 45, "source": "Persian"}, {"target": "Pidgeot", "value": 8, "source": "Psyduck"}, {"target": "Charizard", "value": 22, "source": "Golduck"}, {"target": "Charizard", "value": 22, "source": "Primeape"}, {"target": "Nidoking", "value": 4, "source": "Growlithe"}, {"target": "Dragonite", "value": 135, "source": "Arcanine"}, {"target": "Starmie", "value": 1, "source": "Poliwag"}, {"target": "Jynx", "value": 1, "source": "Poliwhirl"}, {"target": "Raichu", "value": 89, "source": "Poliwrath"}, {"target": "Ditto", "value": 2, "source": "Abra"}, {"target": "Articuno", "value": 17, "source": "Kadabra"}, {"target": "Tauros", "value": 107, "source": "Alakazam"}, {"target": "Machamp", "value": 2, "source": "Machoke"}, {"target": "Dragonite", "value": 96, "source": "Machamp"}, {"target": "Marowak", "value": 3, "source": "Weepinbell"}, {"target": "Electabuzz", "value": 32, "source": "Victreebel"}, {"target": "Dragonite", "value": 69, "source": "Tentacruel"}, {"target": "Onix", "value": 8, "source": "Geodude"}, {"target": "Onix", "value": 9, "source": "Graveler"}, {"target": "Gengar", "value": 233, "source": "Golem"}, {"target": "Rapidash", "value": 1, "source": "Ponyta"}, {"target": "Venusaur", "value": 19, "source": "Rapidash"}, {"target": "Pinsir", "value": 2, "source": "Slowpoke"}, {"target": "Chansey", "value": 121, "source": "Slowbro"}, {"target": "Magneton", "value": 4, "source": "Magnemite"}, {"target": "Dodrio", "value": 26, "source": "Magneton"}, {"target": "Hitmonchan", "value": 6, "source": "Farfetch'd"}, {"target": "Venusaur", "value": 73, "source": "Dodrio"}, {"target": "Horsea", "value": 4, "source": "Seel"}, {"target": "Arbok", "value": 20, "source": "Dewgong"}, {"target": "Charizard", "value": 36, "source": "Muk"}, {"target": "Gengar", "value": 361, "source": "Cloyster"}, {"target": "Haunter", "value": 5, "source": "Gastly"}, {"target": "Kadabra", "value": 16, "source": "Haunter"}, {"target": "Cloyster", "value": 354, "source": "Gengar"}, {"target": "Ditto", "value": 37, "source": "Onix"}, {"target": "Wartortle", "value": 3, "source": "Drowzee"}, {"target": "Clefable", "value": 149, "source": "Hypno"}, {"target": "Machamp", "value": 7, "source": "Krabby"}, {"target": "Charizard", "value": 34, "source": "Kingler"}, {"target": "Electrode", "value": 6, "source": "Voltorb"}, {"target": "Gengar", "value": 52, "source": "Electrode"}, {"target": "Kadabra", "value": 2, "source": "Exeggcute"}, {"target": "Tauros", "value": 1866, "source": "Exeggutor"}, {"target": "Kabuto", "value": 1, "source": "Cubone"}, {"target": "Dragonite", "value": 39, "source": "Marowak"}, {"target": "Charizard", "value": 110, "source": "Hitmonlee"}, {"target": "Charizard", "value": 29, "source": "Hitmonchan"}, {"target": "Arbok", "value": 25, "source": "Lickitung"}, {"target": "Weezing", "value": 1, "source": "Koffing"}, {"target": "Electrode", "value": 23, "source": "Weezing"}, {"target": "Onix", "value": 6, "source": "Rhyhorn"}, {"target": "Arcanine", "value": 48, "source": "Rhydon"}, {"target": "Tauros", "value": 2188, "source": "Chansey"}, {"target": "Porygon", "value": 22, "source": "Tangela"}, {"target": "Persian", "value": 30, "source": "Kangaskhan"}, {"target": "Staryu", "value": 6, "source": "Horsea"}, {"target": "Gyarados", "value": 27, "source": "Seadra"}, {"target": "Horsea", "value": 1, "source": "Goldeen"}, {"target": "Golduck", "value": 2, "source": "Seaking"}, {"target": "Starmie", "value": 7, "source": "Staryu"}, {"target": "Tauros", "value": 1346, "source": "Starmie"}, {"target": "Dodrio", "value": 11, "source": "Mr. Mime"}, {"target": "Charizard", "value": 57, "source": "Scyther"}, {"target": "Tauros", "value": 589, "source": "Jynx"}, {"target": "Dragonite", "value": 42, "source": "Electabuzz"}, {"target": "Venusaur", "value": 26, "source": "Magmar"}, {"target": "Poliwrath", "value": 14, "source": "Pinsir"}, {"target": "Chansey", "value": 2190, "source": "Tauros"}, {"target": "Metapod", "value": 4, "source": "Magikarp"}, {"target": "Dragonite", "value": 203, "source": "Gyarados"}, {"target": "Charizard", "value": 333, "source": "Lapras"}, {"target": "Dragonite", "value": 45, "source": "Ditto"}, {"target": "Sandslash", "value": 5, "source": "Eevee"}, {"target": "Charizard", "value": 69, "source": "Vaporeon"}, {"target": "Lapras", "value": 222, "source": "Jolteon"}, {"target": "Venusaur", "value": 36, "source": "Flareon"}, {"target": "Tangela", "value": 22, "source": "Porygon"}, {"target": "Farfetch'd", "value": 2, "source": "Omanyte"}, {"target": "Venomoth", "value": 30, "source": "Omastar"}, {"target": "Omanyte", "value": 1, "source": "Kabuto"}, {"target": "Articuno", "value": 29, "source": "Kabutops"}, {"target": "Dragonite", "value": 60, "source": "Aerodactyl"}, {"target": "Exeggutor", "value": 745, "source": "Snorlax"}, {"target": "Moltres", "value": 174, "source": "Articuno"}, {"target": "Tauros", "value": 204, "source": "Zapdos"}, {"target": "Articuno", "value": 174, "source": "Moltres"}, {"target": "Kabutops", "value": 23, "source": "Dratini"}, {"target": "Cloyster", "value": 40, "source": "Dragonair"}, {"target": "Charizard", "value": 380, "source": "Dragonite"}]}